{
  "_class": "shapeGroup",
  "booleanOperation": -1,
  "clippingMaskMode": 0,
  "do_objectID": "46FFD9D4-66A0-4C84-BE73-DD3515B59C37",
  "exportOptions": {
    "_class": "exportOptions",
    "do_objectID": "0688B96A-BCA4-4EF4-8C69-0DF711054775",
    "exportFormats": [
    ],
    "includedLayerIds": [
    ],
    "layerOptions": 0,
    "shouldTrim": false
  },
  "frame": {
    "_class": "rect",
    "constrainProportions": true,
    "do_objectID": "2FDD72CA-4537-4BE9-AA09-809430ED6FEF",
    "height": 40,
    "width": 40,
    "x": 12,
    "y": 17
  },
  "hasClickThrough": false,
  "hasClippingMask": false,
  "isFixedToViewport": false,
  "isFlippedHorizontal": false,
  "isFlippedVertical": false,
  "isLocked": false,
  "isVisible": true,
  "layerListExpandedType": 1,
  "layers": [
    {
      "class": "shapePath",
      "id": "11006DB0-DA7C-4392-A963-4392DD753E50"
    },
    {
      "class": "shapePath",
      "id": "C1D721E9-916F-4D99-8DCD-D118D6F1C928"
    },
    {
      "class": "shapePath",
      "id": "CFA904C4-6ADF-4872-AA8C-7F17B17E890C"
    }
  ],
  "name": "ion-information-circled - Ionicons",
  "nameIsFixed": false,
  "resizingConstraint": 41,
  "resizingType": 0,
  "rotation": 0,
  "shouldBreakMaskChain": false,
  "style": {
    "_class": "style",
    "do_objectID": "4C1B2531-3A97-4D22-BB0D-EB6CA43A8BF1",
    "endMarkerType": 0,
    "fills": [
      {
        "_class": "fill",
        "color": {
          "_class": "color",
          "alpha": 1,
          "blue": 0.2666666666666667,
          "green": 0.615686274509804,
          "red": 0.2666666666666667
        },
        "fillType": 0,
        "isEnabled": true,
        "noiseIndex": 0,
        "noiseIntensity": 0,
        "patternFillType": 1,
        "patternTileScale": 1
      }
    ],
    "miterLimit": 10,
    "startMarkerType": 0,
    "textStyle": {
      "_class": "textStyle",
      "do_objectID": "3B7DFD58-7811-4BCD-8EDF-9256189DA3B0",
      "encodedAttributes": {
        "MSAttributedStringColorAttribute": {
          "_class": "color",
          "alpha": 1,
          "blue": 0.01568627450980383,
          "green": 0.5607843137254903,
          "red": 0.9921568627450981
        },
        "MSAttributedStringFontAttribute": {
          "_class": "fontDescriptor",
          "attributes": {
            "name": "Ionicons",
            "size": 49
          }
        }
      },
      "verticalAlignment": 0
    },
    "windingRule": 1
  },
  "windingRule": 1
}